MANIFEST.in
README.md
requirements.txt
setup.cfg
setup.py
TNODatabase/MPCRecord.py
TNODatabase/TNODatabase.py
TNODatabase/TNOTools.py
TNODatabase/__init__.py
TNODatabase.egg-info/PKG-INFO
TNODatabase.egg-info/SOURCES.txt
TNODatabase.egg-info/dependency_links.txt
TNODatabase.egg-info/requires.txt
TNODatabase.egg-info/top_level.txt