Metadata-Version: 1.1
Name: TNODatabase
Version: 0.1.1
Summary: Python module for interacting with Trans-Neptunian Object Database on DESOPER. Use requires a working DES username & password.
Home-page: https://github.com/kfranson/TNODatabase
Author: Kyle Franson, Lynus Zullo
Author-email: kfranson@umich.edu lzullo@umich.edu
License: BSD
Download-URL: https://github.com/kfranson/TNODatabase/tarball/0.1.1
Platform: UNKNOWN
Classifier: Development Status :: 3 - Alpha
Classifier: Intended Audience :: Developers
Classifier: Programming Language :: Python :: 3
